aggexif/__init__.py
aggexif/aggeixf_argument.py
aggexif/aggregator.py
aggexif/exif_parser.py
aggexif/exif_time_parser.py
aggexif/filter_cond.py
aggexif/group.py
aggexif/main.py
aggexif/printer.py
aggexif/sqlite_cache.py
aggexif/termgraph.py
aggexif-0.4.1.dist-info/entry_points.txt
aggexif-0.4.1.dist-info/LICENSE
aggexif-0.4.1.dist-info/WHEEL
aggexif-0.4.1.dist-info/METADATA
aggexif-0.4.1.dist-info/RECORD
