Metadata-Version: 2.1
Name: aggexif
Version: 0.4.1
Summary: Aggregate Image's EXIF Tool
Home-page: https://github.com/ponkotuy/python-exif
License: Apache-2.0
Author: ponkotuy
Author-email: web@ponkotuy.com
Requires-Python: >=3.8,<4.0
Classifier: License :: OSI Approved :: Apache Software License
Classifier: Programming Language :: Python :: 3
Classifier: Programming Language :: Python :: 3.10
Classifier: Programming Language :: Python :: 3.8
Classifier: Programming Language :: Python :: 3.9
